moudle/Log.py
moudle/__init__.py
moudle/basepage.py
moudle/public.py
moudle/utils_luTuo.py
LT666-8.8.dist-info/LICENSE
LT666-8.8.dist-info/METADATA
LT666-8.8.dist-info/WHEEL
LT666-8.8.dist-info/top_level.txt
LT666-8.8.dist-info/RECORD
