Metadata-Version: 2.1
Name: LT666
Version: 8.8
Summary: luTuo
Author: LT
Author-email: 1803228677@qq.com
Requires-Python: >=3.6
License-File: LICENSE
